seenoevil/__init__.py
seenoevil/__main__.py
seenoevil/model.py
seenoevil/server.py
seenoevil/settings.py
seenoevil/static/app.js
seenoevil/static/styles.css
seenoevil/templates/base.html
seenoevil/templates/create.html
seenoevil/templates/index.html
seenoevil/templates/show.html
seenoevil-0.1.2.data/scripts/seenoevil
seenoevil-0.1.2.dist-info/LICENSE
seenoevil-0.1.2.dist-info/METADATA
seenoevil-0.1.2.dist-info/WHEEL
seenoevil-0.1.2.dist-info/top_level.txt
seenoevil-0.1.2.dist-info/RECORD
