Metadata-Version: 2.1
Name: seenoevil
Version: 0.1.2
Summary: Client side encrypted pastebin.
Home-page: https://github.com/jorgebg/seenoevil
Author: Jorge Barata
Author-email: jorge.barata.gonzalez@gmail.com
License: GPLv2
Platform: UNKNOWN
Classifier: License :: OSI Approved :: GNU General Public License v2 (GPLv2)
Classifier: Programming Language :: JavaScript
Classifier: Programming Language :: Python
Classifier: Programming Language :: Python :: 3
Classifier: Programming Language :: Python :: 3.6
Classifier: Programming Language :: Python :: Implementation :: CPython
Classifier: Programming Language :: Python :: Implementation :: PyPy
Requires-Python: >=3.6.0
Requires-Dist: sanic (==19.3.1)
Requires-Dist: sanic-jinja2 (==0.7.4)
Requires-Dist: peewee (==3.9.4)
Requires-Dist: itsdangerous (==1.1.0)
Requires-Dist: environs (==4.1.0)
